kong/__init__.py
kong/cli.py
kong/config.py
kong/db.py
kong/drivers/__init__.py
kong/drivers/batch_driver_base.py
kong/drivers/driver_base.py
kong/drivers/htcondor_driver.py
kong/drivers/local_driver.py
kong/drivers/slurm_driver.py
kong/executor.py
kong/json_field.py
kong/logger.py
kong/model/__init__.py
kong/model/folder.py
kong/model/job.py
kong/repl.py
kong/setup.py
kong/state.py
kong/table.py
kong/util.py
kong_batch-0.9.4.dist-info/entry_points.txt
kong_batch-0.9.4.dist-info/LICENSE
kong_batch-0.9.4.dist-info/WHEEL
kong_batch-0.9.4.dist-info/METADATA
kong_batch-0.9.4.dist-info/RECORD
