Metadata-Version: 2.1
Name: kong-batch
Version: 0.9.4
Summary: Batch job submission and management tool
Home-page: https://github.com/paulgessinger/kong/
License: MIT
Author: Paul Gessinger
Author-email: hello@paulgessinger.com
Requires-Python: >=3.6,<4.0
Classifier: License :: OSI Approved :: MIT License
Classifier: Programming Language :: Python :: 3
Classifier: Programming Language :: Python :: 3.6
Classifier: Programming Language :: Python :: 3.7
Classifier: Programming Language :: Python :: 3.8
Provides-Extra: ipython
Requires-Dist: click (>=7.1.2,<8.0.0)
Requires-Dist: coloredlogs (>=14.0,<15.0)
Requires-Dist: halo (>=0.0.29,<0.0.31)
Requires-Dist: humanfriendly (>=8.2,<9.0)
Requires-Dist: ipython (>=7.16.1,<8.0.0); extra == "ipython"
Requires-Dist: jinja2 (>=2.11.2,<3.0.0)
Requires-Dist: notifiers (>=1.2.1,<2.0.0)
Requires-Dist: peewee (>=3.13.3,<4.0.0)
Requires-Dist: psutil (>=5.7.2,<6.0.0)
Requires-Dist: python-dateutil (>=2.8.1,<3.0.0)
Requires-Dist: pytimeparse (>=1.1.8,<2.0.0)
Requires-Dist: pytz (>=2020.1,<2021.0)
Requires-Dist: pyyaml (>=5.3.1,<6.0.0)
Requires-Dist: schema (>=0.7.2,<0.8.0)
Requires-Dist: sh (>=1.13.1,<2.0.0)
Requires-Dist: tqdm (>=4.48.0,<5.0.0)
